redactyl/__init__.py
redactyl/batch.py
redactyl/callbacks.py
redactyl/core.py
redactyl/entity_tracker.py
redactyl/exceptions.py
redactyl/handlers.py
redactyl/protocols.py
redactyl/pydantic_integration.py
redactyl/session.py
redactyl/types.py
redactyl/utils.py
redactyl/detectors/__init__.py
redactyl/detectors/base.py
redactyl/detectors/gliner_parser.py
redactyl/detectors/mock.py
redactyl/detectors/presidio.py
redactyl/detectors/smart_mock.py
redactyl-0.4.1.dist-info/METADATA
redactyl-0.4.1.dist-info/WHEEL
redactyl-0.4.1.dist-info/licenses/LICENSE
redactyl-0.4.1.dist-info/RECORD
