Metadata-Version: 2.4
Name: redactyl
Version: 0.4.1
Summary: Fast, deterministic PII redaction using type-preserving tokens ([NAME_1], [EMAIL_2]) with perfect reversibility
Project-URL: Documentation, https://github.com/screensailor/redactyl#readme
Project-URL: Homepage, https://github.com/screensailor/redactyl
Project-URL: Issues, https://github.com/screensailor/redactyl/issues
Project-URL: Repository, https://github.com/screensailor/redactyl
Author: screensailor
License: MIT
License-File: LICENSE
Keywords: ai,anonymization,data-protection,gdpr,gliner,llm,pii,presidio,privacy,redaction
Classifier: Development Status :: 3 - Alpha
Classifier: Intended Audience :: Developers
Classifier: License :: OSI Approved :: MIT License
Classifier: Programming Language :: Python :: 3
Classifier: Programming Language :: Python :: 3.12
Classifier: Topic :: Scientific/Engineering :: Artificial Intelligence
Classifier: Topic :: Security
Classifier: Topic :: Software Development :: Libraries :: Python Modules
Classifier: Topic :: Text Processing :: Linguistic
Requires-Python: <3.14,>=3.12
Requires-Dist: nameparser>=1.1.0
Requires-Dist: presidio-analyzer>=2.2.0
Requires-Dist: presidio-anonymizer>=2.2.0
Requires-Dist: pydantic>=2.0
Requires-Dist: spacy>=3.8.7
Provides-Extra: gliner
Requires-Dist: gliner>=0.2.21; extra == 'gliner'
